{
  "items": [
    {
      "type": "file",
      "ctime": 1783448076936,
      "path": "01_Characters/PCs/Hunter Moonshine/Hunter Moonshine.md",
      "title": "chractorSheet"
    },
    {
      "type": "file",
      "ctime": 1783448102871,
      "path": "01_Characters/NPCs/Companions/Hunter's Companion/Storm.md",
      "title": "Stormy"
    },
    {
      "type": "file",
      "ctime": 1783448123584,
      "path": "01_Characters/PCs/Hunter Moonshine/a. Index of revisions.md",
      "title": "stormy"
    }
  ]
}